Workbook

Sheet Simulador
B5: Configurações
B6: Salario | D6: 5000
B7: Rendimento Carteira | D7: 0.006
B8: Sugestão de Investimento (30%) | D8: =D6*30% -> 1500
B10: INVESTIMENTO MENSAL
B11: Quanto investir por mês ? | D11: 500
B12: Por quantos anos? | D12: 5
B13: Taxa de investimento mensais? | D13: 0.01079
B14: Patrimonio acumulado? | D14: =FV(D13,D12*12,D11*-1) -> 41888.457
B15: Dividendos Mensais? | D15: =D14*D13 -> 451.97645
B17: CENÁRIOS | D17: Dividendos
A18: 2 | B18: Quantidade em 2 Anos? | C18: =FV($D$13,$A18*12,$D$11*-1) -> 13613.814 | D18: =C18*$D$7 -> 81.682882
A19: 5 | B19: Quantidade em 5 Anos? | C19: =FV($D$13,A19*12,$D$11*-1) -> 41888.457 | D19: =C19*$D$7 -> 251.33074
A20: 10 | B20: Quantidade em 10 Anos? | C20: =FV($D$13,A20*12,$D$11*-1) -> 121642.11 | D20: =C20*$D$7 -> 729.85264
A21: 20 | B21: Quantidade em 20 Anos? | C21: =FV($D$13,A21*12,$D$11*-1) -> 562599.2 | D21: =C21*$D$7 -> 3375.5952
A22: 30 | B22: Quantidade em 30 Anos? | C22: =FV($D$13,A22*12,$D$11*-1) -> 2161084.8 | D22: =C22*$D$7 -> 12966.509
B24: PERFIL | C24: CONSERVADOR
B25: VALOR A SER INVESTIDO POR MÊS | C25: =D11 -> 500
B27: TIPO DE Fll | C27: Porcetual Sugerido
B28: PAPEL | C28: =VLOOKUP($C$24&"-"&B28,'Apoio C. Invest'!$A:$D,4,FALSE) -> 0.5 | D28: =C28*$C$25 -> 250
B29: TIJOLO | C29: =VLOOKUP($C$24&"-"&B29,'Apoio C. Invest'!$A:$D,4,FALSE) -> 0.1 | D29: =C29*$C$25 -> 50
B30: HIBRIDOS | C30: =VLOOKUP($C$24&"-"&B30,'Apoio C. Invest'!$A:$D,4,FALSE) -> 0.05 | D30: =C30*$C$25 -> 25
B31: FOF´s | C31: =VLOOKUP($C$24&"-"&B31,'Apoio C. Invest'!$A:$D,4,FALSE) -> 0.05 | D31: =C31*$C$25 -> 25
B32: DESENVOLVIMENTO | C32: =VLOOKUP($C$24&"-"&B32,'Apoio C. Invest'!$A:$D,4,FALSE) -> 0.2 | D32: =C32*$C$25 -> 100
B33: HOTELARIAS | C33: =VLOOKUP($C$24&"-"&B33,'Apoio C. Invest'!$A:$D,4,FALSE) -> 0.1 | D33: =C33*$C$25 -> 50
B34: TOTAL | D34: =SUM(D28:D33) -> 500

Sheet Apoio C. Invest
A2: PERFIL | C2: TIPO DE Fll | D2: Porcetual Sugerido
A3: AGRESSIVO-PAPEL | B3: AGRESSIVO | C3: PAPEL | D3: 0.3
A4: AGRESSIVO-TIJOLO | B4: AGRESSIVO | C4: TIJOLO | D4: 0.5
A5: AGRESSIVO-HIBRIDOS | B5: AGRESSIVO | C5: HIBRIDOS | D5: 0.1
A6: AGRESSIVO-FOF´s | B6: AGRESSIVO | C6: FOF´s | D6: 0.1
A7: AGRESSIVO-DESENVOLVIMENTO | B7: AGRESSIVO | C7: DESENVOLVIMENTO | D7: 0
A8: AGRESSIVO-HOTELARIAS | B8: AGRESSIVO | C8: HOTELARIAS | D8: 0
A9: MODERADO-PAPEL | B9: MODERADO | C9: PAPEL | D9: 0.32
A10: MODERADO-TIJOLO | B10: MODERADO | C10: TIJOLO | D10: 0.35
A11: MODERADO-HIBRIDOS | B11: MODERADO | C11: HIBRIDOS | D11: 0.08
A12: MODERADO-FOF´s | B12: MODERADO | C12: FOF´s | D12: 0.05
A13: MODERADO-DESENVOLVIMENTO | B13: MODERADO | C13: DESENVOLVIMENTO | D13: 0.1
A14: MODERADO-HOTELARIAS | B14: MODERADO | C14: HOTELARIAS | D14: 0.1
... A20: CONSERVADOR-HOTELARIAS | B20: CONSERVADOR | C20: HOTELARIAS | D20: 0.1
